mmisdk/__init__.py
mmisdk/adapters/bitgo_adapter.py
mmisdk/adapters/bitgo_adapter_test.py
mmisdk/adapters/bitgo_create_tx_extra_params.py
mmisdk/adapters/cactus_adapter.py
mmisdk/adapters/cactus_adapter_test.py
mmisdk/adapters/cactus_create_tx_extra_params.py
mmisdk/adapters/jsonrpc_adapter.py
mmisdk/adapters/jsonrpc_adapter_test.py
mmisdk/adapters/qredo_adapter.py
mmisdk/adapters/qredo_adapter_test.py
mmisdk/adapters/qredo_create_tx_extra_params.py
mmisdk/bitgo/bitgo_client.py
mmisdk/bitgo/bitgo_client_test.py
mmisdk/bitgo/bitgo_create_tx_params.py
mmisdk/bitgo/bitgo_list_response.py
mmisdk/bitgo/bitgo_response.py
mmisdk/bitgo/bitgo_response_meta.py
mmisdk/bitgo/bitgo_transaction.py
mmisdk/cactus/cactus_client.py
mmisdk/cactus/cactus_client_test.py
mmisdk/cactus/cactus_get_transactions_params.py
mmisdk/cactus/cactus_transaction_detail.py
mmisdk/cactus/cactus_tx_params.py
mmisdk/common/__init__.py
mmisdk/common/abstract_client.py
mmisdk/common/base_model.py
mmisdk/common/custodian.py
mmisdk/common/dec_string.py
mmisdk/common/empty_string.py
mmisdk/common/ethereum_address.py
mmisdk/common/hex_string.py
mmisdk/common/transaction.py
mmisdk/common/transaction_params.py
mmisdk/factory/custodian_factory.py
mmisdk/factory/custodian_factory_test.py
mmisdk/factory/custodian_name_to_client_adapter.py
mmisdk/jsonrpc/jsonrpc_client.py
mmisdk/jsonrpc/jsonrpc_client_test.py
mmisdk/jsonrpc/jsonrpc_create_transaction_metadata.py
mmisdk/jsonrpc/jsonrpc_create_transaction_params.py
mmisdk/jsonrpc/jsonrpc_error.py
mmisdk/jsonrpc/jsonrpc_get_transaction_result.py
mmisdk/jsonrpc/jsonrpc_request.py
mmisdk/jsonrpc/jsonrpc_response.py
mmisdk/jsonrpc/jsonrpc_transaction_id.py
mmisdk/jsonrpc/jsonrpc_transaction_status.py
mmisdk/mmiconfig/custodian_config.py
mmisdk/mmiconfig/mmi_config.py
mmisdk/mmiconfig/mmiconfig_client.py
mmisdk/mmiconfig/mmiconfig_client_test.py
mmisdk/mmiconfig/mmiconfig_legacy_override.py
mmisdk/mocks/mock_bitgo_create_tx_response.py
mmisdk-0.5.1.dist-info/AUTHORS.md
mmisdk-0.5.1.dist-info/METADATA
mmisdk-0.5.1.dist-info/WHEEL
mmisdk-0.5.1.dist-info/top_level.txt
mmisdk-0.5.1.dist-info/RECORD
